LICENSE.txt
MANIFEST.in
README.rst
setup.cfg
setup.py
tw2/__init__.py
tw2.slideymenu.egg-info/PKG-INFO
tw2.slideymenu.egg-info/SOURCES.txt
tw2.slideymenu.egg-info/dependency_links.txt
tw2.slideymenu.egg-info/entry_points.txt
tw2.slideymenu.egg-info/namespace_packages.txt
tw2.slideymenu.egg-info/not-zip-safe
tw2.slideymenu.egg-info/requires.txt
tw2.slideymenu.egg-info/top_level.txt
tw2/slideymenu/__init__.py
tw2/slideymenu/base.py
tw2/slideymenu/samples.py
tw2/slideymenu/widgets.py
tw2/slideymenu/static/css/slidey.css
tw2/slideymenu/static/js/slidey.js
tw2/slideymenu/templates/__init__.py
tw2/slideymenu/templates/menu.mak